py_ssa_lib/MSSA.py
py_ssa_lib/SSA.py
py_ssa_lib/__init__.py
py_ssa_lib/.ipynb_checkpoints/MSSA-checkpoint.py
py_ssa_lib/.ipynb_checkpoints/SSA-checkpoint.py
py_ssa_lib/datasets/GlobalLandTemperaturesByMajorCity.csv
py_ssa_lib/datasets/__init__.py
py_ssa_lib/datasets/energy_consumption_df.csv
py_ssa_lib/datasets/load_energy_consumption_df.py
py_ssa_lib/datasets/load_global_average_temperatures_df.py
py_ssa_lib/datasets/total-primary-energy-consumption-csv-version-4.csv
py_ssa_lib/datasets/.ipynb_checkpoints/load_energy_consumption_df-checkpoint.py
py_ssa_lib/datasets/.ipynb_checkpoints/load_global_average_temperatures-checkpoint.py
py_ssa_lib-1.2.4.1.dist-info/LICENSE.txt
py_ssa_lib-1.2.4.1.dist-info/METADATA
py_ssa_lib-1.2.4.1.dist-info/WHEEL
py_ssa_lib-1.2.4.1.dist-info/top_level.txt
py_ssa_lib-1.2.4.1.dist-info/RECORD
