Metadata-Version: 2.1
Name: py_ssa_lib
Version: 1.2.4.1
Summary: "This package implements MSSA and SSA in Python, which are used for time series decomposition, forecasting values and estimation of roots of signals"
Home-page: https://github.com/K-Ibadullaev/py_ssa
Author: Konstantin Ibadullaev
License: GPL-3.0-or-later
Requires-Python: >=3.10.0
License-File: LICENSE.txt
Requires-Dist: numpy>=2.0.0
Requires-Dist: matplotlib>=3.9.0
Requires-Dist: scipy>=1.14.0
Requires-Dist: scikit-learn>=1.5.0
Requires-Dist: pandas>=2.0.0
